myhttps/__init__.py
myhttps/__main__.py
myhttps/_myhttps.py
myhttps/test.py
myhttps-0.0.28.dist-info/LICENSE
myhttps-0.0.28.dist-info/METADATA
myhttps-0.0.28.dist-info/WHEEL
myhttps-0.0.28.dist-info/entry_points.txt
myhttps-0.0.28.dist-info/top_level.txt
myhttps-0.0.28.dist-info/RECORD
