Metadata-Version: 2.1
Name: myhttps
Version: 0.0.28
Home-page: https://github.com/leeyang1991/myhttps
Author: Yang Li
Author-email: leeyang1991@gmail.com
Requires-Python: >=3
License-File: LICENSE
Requires-Dist: pyOpenSSL
Requires-Dist: outdated
Requires-Dist: urllib3
Requires-Dist: requests
Requires-Dist: beautifulsoup4
Requires-Dist: ifcfg
